PwStrength/PwStrength.py
PwStrength/__init__.py
PwStrength-0.2.0.dist-info/LICENSE
PwStrength-0.2.0.dist-info/METADATA
PwStrength-0.2.0.dist-info/WHEEL
PwStrength-0.2.0.dist-info/top_level.txt
PwStrength-0.2.0.dist-info/RECORD
